subunit/__init__.py
subunit/_output.py
subunit/_to_disk.py
subunit/chunked.py
subunit/details.py
subunit/filters.py
subunit/iso8601.py
subunit/progress_model.py
subunit/run.py
subunit/test_results.py
subunit/v2.py
subunit/tests/__init__.py
subunit/tests/sample-script.py
subunit/tests/sample-two-script.py
subunit/tests/test_chunked.py
subunit/tests/test_details.py
subunit/tests/test_filter_to_disk.py
subunit/tests/test_filters.py
subunit/tests/test_output_filter.py
subunit/tests/test_progress_model.py
subunit/tests/test_run.py
subunit/tests/test_subunit_filter.py
subunit/tests/test_subunit_stats.py
subunit/tests/test_subunit_tags.py
subunit/tests/test_tap2subunit.py
subunit/tests/test_test_protocol.py
subunit/tests/test_test_protocol2.py
subunit/tests/test_test_results.py
subunit-0.0.0a0.data/scripts/subunit-1to2
subunit-0.0.0a0.data/scripts/subunit-2to1
subunit-0.0.0a0.data/scripts/subunit-filter
subunit-0.0.0a0.data/scripts/subunit-ls
subunit-0.0.0a0.data/scripts/subunit-notify
subunit-0.0.0a0.data/scripts/subunit-output
subunit-0.0.0a0.data/scripts/subunit-stats
subunit-0.0.0a0.data/scripts/subunit-tags
subunit-0.0.0a0.data/scripts/subunit2csv
subunit-0.0.0a0.data/scripts/subunit2disk
subunit-0.0.0a0.data/scripts/subunit2gtk
subunit-0.0.0a0.data/scripts/subunit2junitxml
subunit-0.0.0a0.data/scripts/subunit2pyunit
subunit-0.0.0a0.data/scripts/tap2subunit
subunit-0.0.0a0.dist-info/COPYING
subunit-0.0.0a0.dist-info/METADATA
subunit-0.0.0a0.dist-info/WHEEL
subunit-0.0.0a0.dist-info/top_level.txt
subunit-0.0.0a0.dist-info/RECORD
