Metadata-Version: 2.1
Name: subunit
Version: 0.0.0a0
Summary: Python implementation of subunit test streaming protocol
Home-page: http://launchpad.net/subunit
Author: Robert Collins
Author-email: subunit-dev@lists.launchpad.net
License: Apache-2.0 or BSD
Project-URL: Bug Tracker, https://bugs.launchpad.net/subunit
Project-URL: Source Code, https://github.com/testing-cabal/subunit/
Keywords: python test streaming
Platform: UNKNOWN
Classifier: Intended Audience :: Developers
Classifier: Operating System :: OS Independent
Classifier: Programming Language :: Python
Classifier: Programming Language :: Python :: 2.7
Classifier: Programming Language :: Python :: 3
Classifier: Programming Language :: Python :: 3.5
Classifier: Programming Language :: Python :: 3.6
Classifier: Programming Language :: Python :: 3.7
Classifier: Programming Language :: Python :: 3.8
Classifier: Topic :: Software Development :: Testing
Requires-Dist: extras
Requires-Dist: testtools (>=0.9.34)
Provides-Extra: docs
Requires-Dist: docutils ; extra == 'docs'
Provides-Extra: test
Requires-Dist: fixtures ; extra == 'test'
Requires-Dist: testscenarios ; extra == 'test'
Requires-Dist: hypothesis ; (python_version!="3.2") and extra == 'test'
